{
  "name": "matriculas/documentos/DNI-41884433-frente-1782972430407-DNI-COMPLETO.pdf",
  "bucket": "cetprosmp-2026.firebasestorage.app",
  "metageneration": 1,
  "generation": 1782972430440,
  "contentType": "application/pdf",
  "storageClass": "STANDARD",
  "contentDisposition": "inline",
  "downloadTokens": [
    "e99499ba-0e57-4e44-8b78-10844b0d1362"
  ],
  "etag": "M4IMm8PNBtsvlAO47+Ljll+JKBA",
  "customMetadata": {},
  "timeCreated": "2026-07-02T06:07:10.440Z",
  "updated": "2026-07-02T06:07:10.440Z",
  "size": 57550,
  "md5Hash": "PVJM0eqy+dppUVaVGy9tfA==",
  "crc32c": "1333721612"
}