{
  "name": "matriculas/documentos/DNI-10698579-frente-1782958881141-dni2-a.jpg",
  "bucket": "cetprosmp-2026.firebasestorage.app",
  "metageneration": 1,
  "generation": 1782958881183,
  "contentType": "image/jpeg",
  "storageClass": "STANDARD",
  "contentDisposition": "inline",
  "downloadTokens": [
    "266498d3-ee97-49d1-9b9d-d0480915da23"
  ],
  "etag": "hHfmv0TIMIe7GZEiRA+8pcz04ZM",
  "customMetadata": {},
  "timeCreated": "2026-07-02T02:21:21.183Z",
  "updated": "2026-07-02T02:21:21.183Z",
  "size": 705588,
  "md5Hash": "JueWiP1xoYCl/eHa7uWKlA==",
  "crc32c": "3897238403"
}