{
  "name": "usuarios/1780293556687_dama4.webp",
  "bucket": "cetprosmp-2026.firebasestorage.app",
  "metageneration": 1,
  "generation": 1780293556745,
  "contentType": "image/webp",
  "storageClass": "STANDARD",
  "contentDisposition": "inline",
  "downloadTokens": [
    "28450cb2-1373-4351-963c-79a4fb658d30"
  ],
  "etag": "JnO3Q1I5um8pv2kt1RucBT6cQEM",
  "customMetadata": {},
  "timeCreated": "2026-06-01T05:59:16.745Z",
  "updated": "2026-06-01T05:59:16.745Z",
  "size": 8490,
  "md5Hash": "+QWtx2/xE4PngWAf8BZVKw==",
  "crc32c": "719065282"
}