{
  "name": "matriculas/documentos/DNI-07254587-reverso-1783197443982-graciela2.jpeg",
  "bucket": "cetprosmp-2026.firebasestorage.app",
  "metageneration": 1,
  "generation": 1783197445746160,
  "contentType": "image/jpeg",
  "storageClass": "REGIONAL",
  "contentDisposition": "inline; filename*=utf-8''DNI-07254587-reverso-1783197443982-graciela2.jpeg",
  "downloadTokens": [
    "ce460d15-acfb-4702-94f8-b3de7e265795"
  ],
  "etag": "CPDbxZLwuZUDEAE=",
  "customMetadata": {},
  "timeCreated": "2026-07-04T20:37:25.763Z",
  "updated": "2026-07-04T20:37:25.763Z",
  "size": 132897,
  "md5Hash": "4szyvI8I/AHjMJCCnE/4Ng==",
  "crc32c": "HBGERQ=="
}